{
    "name": "Document",
    "fields": [
        {
            "fieldName": "titre",
            "fieldType": "String"
        },
        {
            "fieldName": "data",
            "fieldType": "byte[]",
            "fieldTypeBlobContent": "any"
        },
        {
            "fieldName": "typeDocument",
            "fieldType": "TypeDocument",
            "fieldValues": "PROFESSEUR,LICENCE,MASTER,MASTER_EXECUTIF",
            "fieldValidateRules": [
                "required"
            ]
        }
    ],
    "relationships": [],
    "changelogDate": "20201022210042",
    "entityTableName": "document",
    "dto": "no",
    "pagination": "no",
    "service": "no",
    "jpaMetamodelFiltering": false,
    "fluentMethods": true,
    "clientRootFolder": "",
    "applications": "*"
}